{
  "project_info": {
    "project_number": "85975781920",
    "project_id": "even-terra-421708",
    "storage_bucket": "even-terra-421708.appspot.com"
  },
  "client": [
    {
      "client_info": {
        "mobilesdk_app_id": "1:85975781920:android:65b0a80f06c84f5838e245",
        "android_client_info": {
          "package_name": "com.example.todo_app_project"
        }
      },
      "oauth_client": [],
      "api_key": [
        {
          "current_key": "AIzaSyBIBMGaWg-zGCoJ9W1-O_Ev8-HQCJUkn2E"
        }
      ],
      "services": {
        "appinvite_service": {
          "other_platform_oauth_client": []
        }
      }
    }
  ],
  "configuration_version": "1"
}